CHANGELOG.md
LICENSE
MANIFEST.in
README.md
dev-requirements.txt
requirements.txt
setup.py
version.py
Eliza.egg-info/PKG-INFO
Eliza.egg-info/SOURCES.txt
Eliza.egg-info/dependency_links.txt
Eliza.egg-info/requires.txt
Eliza.egg-info/top_level.txt
docs/code.rst
docs/config.rst
docs/contribution.rst
docs/index.rst
docs/install.rst
docs/license.rst
eliza/__init__.py
eliza/config.py
eliza/errors.py
test/test_config.py