Metadata-Version: 2.1
Name: Eliza
Version: 1.0.3
Summary: Library with common features for Python (Flask) Microservices
Home-page: https://github.com/redvox/Eliza
Download-URL: https://github.com/redvox/Eliza/tarball/1.0.3
Author: Jens Schaa
Author-email: jens.schaa@posteo.de
License: Apache Software License
License-File: LICENSE
